phoenix/__init__.py
phoenix/phoenix.py
phoenix/data/sepsis.csv
phoenix_sepsis-1.1.3.dist-info/licenses/LICENSE
phoenix_sepsis-1.1.3.dist-info/METADATA
phoenix_sepsis-1.1.3.dist-info/WHEEL
phoenix_sepsis-1.1.3.dist-info/top_level.txt
phoenix_sepsis-1.1.3.dist-info/RECORD
