Metadata-Version: 2.4
Name: phoenix_sepsis
Version: 1.1.3
Summary: Implementation of the Phoenix and Phoenix-8 Pediatric Sepsis Criteria
Author-email: "Peter E. DeWitt" <peter.dewitt@cuanschutz.edu>, Seth Russell <seth.russell@cuanschutz.edu>, Meg Rebull <meg.rebull@cuanschutz.edu>, Tell Bennett <tell.bennett@cuanschutz.edu>, "L. Nelson Sanchez-Pinto" <lsanchezpinto@luriechildrens.org>
Project-URL: Homepage, https://cu-dbmi-peds.github.io/phoenix/index.html
Project-URL: Issues, https://github.com/CU-DBMI-Peds/phoenix/issues
License-File: LICENSE
Requires-Dist: numpy
Requires-Dist: pandas
Dynamic: license-file
